macropy/__main__.py
macropy/common.cp310-win_amd64.pyd
macropy/configurations.py
macropy/eventListeners.cp310-win_amd64.pyd
macropy/explorerHelper.cp310-win_amd64.pyd
macropy/imageInverter.cp310-win_amd64.pyd
macropy/keyboardHelper.cp310-win_amd64.pyd
macropy/scriptController.cp310-win_amd64.pyd
macropy/systemHelper.cp310-win_amd64.pyd
macropy/windowHelper.cp310-win_amd64.pyd
macropy/Images/static/keyboard (0.5).png
macropy/Images/static/keyboard.png
macropy/SFX/achievement-message-tone.wav
macropy/SFX/coins-497.wav
macropy/SFX/connection-sound.wav
macropy/SFX/crack_the_whip.wav
macropy/SFX/denied.wav
macropy/SFX/knob-458.wav
macropy/SFX/no-trespassing-368.wav
macropy/SFX/pedantic-490.wav
macropy/SFX/record-scratch-2.mp3
macropy/SFX/tts_temp1.wav
macropy/SFX/wrong.swf.wav
kb_macropy-0.0.24.dist-info/LICENSE.txt
kb_macropy-0.0.24.dist-info/METADATA
kb_macropy-0.0.24.dist-info/WHEEL
kb_macropy-0.0.24.dist-info/entry_points.txt
kb_macropy-0.0.24.dist-info/top_level.txt
kb_macropy-0.0.24.dist-info/RECORD
