Metadata-Version: 2.1
Name: kb-macropy
Version: 0.0.24
Summary: Keyboard listener and automation script.
Home-page: https://github.com/Ryen-042/macropy
Author: Ahmed Tarek
Author-email: ahmedtarek4377@gmail.com
License: MIT
Keywords: keyboard automation script
Platform: UNKNOWN
Classifier: Development Status :: 5 - Production/Stable
Classifier: Environment :: Console
Classifier: Environment :: Win32 (MS Windows)
Classifier: Intended Audience :: Developers
Classifier: License :: OSI Approved :: MIT License
Classifier: Programming Language :: Python
Classifier: Programming Language :: Python :: 3
Classifier: Programming Language :: Python :: 3.6
Classifier: Programming Language :: Python :: 3.7
Classifier: Programming Language :: Python :: 3.8
Classifier: Programming Language :: Python :: 3.9
Classifier: Programming Language :: Python :: 3.10
Classifier: Programming Language :: Cython
Classifier: Topic :: Utilities
License-File: LICENSE.txt
Requires-Dist: img2pdf
Requires-Dist: keyboard
Requires-Dist: opencv-python
Requires-Dist: Pillow
Requires-Dist: psutil
Requires-Dist: PyAudio
Requires-Dist: pynput
Requires-Dist: pyttsx3
Requires-Dist: pywin32
Requires-Dist: pyWinhook
Requires-Dist: win11toast
Requires-Dist: WMI
